[
  {
    "id": 1,
    "agency": "NHAI",
    "work": "Status of Elevated Road Ramp.",
    "completionDate": "2024-06-15",
    "status": "In Progress"
  },
  {
    "id": 2,
    "agency": "NHAI",
    "work": "Status of Ludhiana–Rupnagar Road. ( package 1 & 2 )",
    "completionDate": "2024-05-10",
    "status": "Completed"
  },
  {
    "id": 3,
    "agency": "NHAI",
    "work": "Status of entry/exit points, cycle track, and new service road at Sherpur.",
    "completionDate": "2024-04-20",
    "status": "Pending"
  },
  {
    "id": 4,
    "agency": "NHAI",
    "work": "Status of entry/exit of Delhi–Katra Highway at Balowal. ( Pakhowal road )",
    "completionDate": "2024-07-01",
    "status": "In Progress"
  },
  {
    "id": 5,
    "agency": "NHAI",
    "work": "Status update on the VUP at Jalandhar bypass",
    "completionDate": "2024-05-25",
    "status": "In Progress"
  },
  {
    "id": 6,
    "agency": "NHAI",
    "work": "Status update on the VUP at Kailash Nagar",
    "completionDate": "2024-05-15",
    "status": "Completed"
  },
  {
    "id": 7,
    "agency": "NHAI",
    "work": "Status update on the Sahnewal junction to be replicate as Samrala chk ludhiana entry & exit for heavy vehicles to avoid jam at junction",
    "completionDate": "2024-08-15",
    "status": "Pending"
  },
  {
    "id": 8,
    "agency": "NHAI",
    "work": "Status update on the Service road and VUP at Dhandari–Jaspal area",
    "completionDate": "2024-03-30",
    "status": "Pending"
  },
  {
    "id": 9,
    "agency": "NHAI",
    "work": "Status Ladhowal ROB widening & median closing",
    "completionDate": "2024-05-30",
    "status": "In Progress"
  },
  {
    "id": 10,
    "agency": "NHAI",
    "work": "Status of bus terminal crossing",
    "completionDate": "2024-06-20",
    "status": "Pending"
  },
  {
    "id": 11,
    "agency": "NHAI",
    "work": "Solution for Atam park junction jam",
    "completionDate": "2024-05-05",
    "status": "Completed"
  },
  {
    "id": 12,
    "agency": "MCL",
    "work": "Preparation and status of DPR for identified traffic bottlenecks. ( Including pspcl land and Model Town dr mittal plot )",
    "completionDate": "2024-06-10",
    "status": "In Progress"
  },
  {
    "id": 13,
    "agency": "MCL",
    "work": "Removal of encroachments and shifting of electric poles.",
    "completionDate": "2024-04-15",
    "status": "Completed"
  },
  {
    "id": 14,
    "agency": "MCL",
    "work": "Street lighting found inadequate; joint action required by MCL, Traffic Police, and PSPCL.",
    "completionDate": "2024-05-10",
    "status": "Pending"
  },
  {
    "id": 15,
    "agency": "MCL",
    "work": "Status of vending zones and no-tolerance zones.",
    "completionDate": "2024-06-30",
    "status": "Pending"
  },
  {
    "id": 16,
    "agency": "MCL",
    "work": "Status of pending traffic lights and removals of old traffic lights in old Sabzi Mandi",
    "completionDate": "2024-05-20",
    "status": "In Progress"
  },
  {
    "id": 17,
    "agency": "MCL",
    "work": "Status of pending traffic lights and removals of old traffic lights in Salem Tabri",
    "completionDate": "2024-05-20",
    "status": "In Progress"
  },
  {
    "id": 18,
    "agency": "MCL",
    "work": "Status of pending traffic lights and removals of old traffic lights in Bharat Nagar Chowk",
    "completionDate": "2024-05-20",
    "status": "In Progress"
  },
  {
    "id": 19,
    "agency": "MCL",
    "work": "Doubling of Focal Point Main Road (Dhandari Bridge to Upper India)",
    "completionDate": "2024-09-01",
    "status": "Pending"
  },
  {
    "id": 20,
    "agency": "MCL",
    "work": "Preparation of new Comprehensive Mobility Plan (CMP), City Transport Plan (CTP), and Logistics Plan in coordination with GLADA (a)Shed at Verka underpass both side",
    "completionDate": "2024-07-15",
    "status": "In Progress"
  },
  {
    "id": 21,
    "agency": "MCL",
    "work": "Preparation of new Comprehensive Mobility Plan (CMP), City Transport Plan (CTP), and Logistics Plan in coordination with GLADA (b) widening of civil line side of station by shifting Shastri hall wall & station Quater",
    "completionDate": "2024-08-15",
    "status": "Pending"
  },
  {
    "id": 22,
    "agency": "MCL",
    "work": "Preparation of new Comprehensive Mobility Plan (CMP), City Transport Plan (CTP), and Logistics Plan in coordination with GLADA (c) Widening if Mall Road at Bharat Nagar junction by shifting sewer board Quater complex wall",
    "completionDate": "2024-08-30",
    "status": "Pending"
  },
  {
    "id": 23,
    "agency": "GLADA",
    "work": "Connectivity of Canal Road with Ferozepur Road (as per Master Plan).",
    "completionDate": "2024-05-15",
    "status": "Completed"
  },
  {
    "id": 24,
    "agency": "GLADA",
    "work": "Connectivity of Pakhowal Road with Ferozepur Road.",
    "completionDate": "2024-05-15",
    "status": "Completed"
  },
  {
    "id": 25,
    "agency": "GLADA",
    "work": "Extension of Cycle Valley Road up to Delhi Road (approx. 3 km).",
    "completionDate": "2024-10-10",
    "status": "In Progress"
  },
  {
    "id": 26,
    "agency": "GLADA",
    "work": "Status of Missing Links 2 & 2.3, including flyover at Gill Road and entry/exit at Canal Road.",
    "completionDate": "2024-04-30",
    "status": "Pending"
  },
  {
    "id": 27,
    "agency": "GLADA",
    "work": "Road connectivity from Ferozepur Road to upcoming Halwara Airport and feasibility of Aero City development.",
    "completionDate": "2024-12-01",
    "status": "Pending"
  },
  {
    "id": 28,
    "agency": "GLADA",
    "work": "Road widening from Baba Tea Stall to Ladhowal Bypass underpass.",
    "completionDate": "2024-06-15",
    "status": "In Progress"
  },
  {
    "id": 29,
    "agency": "GLADA",
    "work": "Rectification and extension of Dehlon Bypass to connect with dry ports to restrict heavy vehicles entering Dehlon town (PWD/GLADA).",
    "completionDate": "2024-07-20",
    "status": "In Progress"
  },
  {
    "id": 30,
    "agency": "GLADA",
    "work": "Development of Inner Ring Road connecting Delhi Road (near Sahnewal Airport) to Jaspal Bangar via Canal Road.",
    "completionDate": "2024-11-15",
    "status": "Pending"
  },
  {
    "id": 31,
    "agency": "GLADA",
    "work": "Status of road development along Budha Dariya in GLADA area.",
    "completionDate": "2024-05-01",
    "status": "Completed"
  },
  {
    "id": 32,
    "agency": "GLADA",
    "work": "Widening of Hambra Road up to Delhi–Katra Expressway entry/exit.",
    "completionDate": "2024-08-01",
    "status": "In Progress"
  },
  {
    "id": 33,
    "agency": "GLADA",
    "work": "Strengthening of roads around entry/exit points of Cycle Valley on Ludhiana–Rupnagar Expressway.",
    "completionDate": "2024-09-15",
    "status": "Pending"
  },
  {
    "id": 34,
    "agency": "Railways",
    "work": "Status of ROB at Doraha–Nelon Road (Ambala Division).",
    "completionDate": "2024-12-31",
    "status": "Pending"
  },
  {
    "id": 35,
    "agency": "Railways",
    "work": "Status of ROB at Dana Mandi.",
    "completionDate": "2024-03-15",
    "status": "Completed"
  },
  {
    "id": 36,
    "agency": "Railways",
    "work": "Status of ROB at Baddowal.",
    "completionDate": "2024-04-10",
    "status": "Pending"
  },
  {
    "id": 37,
    "agency": "Railways",
    "work": "Feasibility of ROB at Sahnewal.",
    "completionDate": "2024-05-30",
    "status": "In Progress"
  },
  {
    "id": 38,
    "agency": "Railways",
    "work": "Feasibility of ROB at Gaspura.",
    "completionDate": "2024-05-30",
    "status": "In Progress"
  },
  {
    "id": 39,
    "agency": "Railways",
    "work": "Feasibility of ROB/Underpass at Sanet.",
    "completionDate": "2024-05-30",
    "status": "In Progress"
  },
  {
    "id": 40,
    "agency": "Railways",
    "work": "Widening of railway crossing between Dugri–GNE Road (Ambala Division).",
    "completionDate": "2024-06-30",
    "status": "Pending"
  },
  {
    "id": 41,
    "agency": "Railways",
    "work": "Status of Foot Over Bridges at Gill Road and Dhandari.",
    "completionDate": "2024-08-20",
    "status": "Pending"
  },
  {
    "id": 42,
    "agency": "Railways",
    "work": "Feasibility of Foot Over Bridges at Sherpur and Vishwakarma Chowk.",
    "completionDate": "2024-10-15",
    "status": "In Progress"
  },
  {
    "id": 43,
    "agency": "Railways",
    "work": "Feasibility of Underpass at Rajguru Nagar.",
    "completionDate": "2024-04-05",
    "status": "Pending"
  },
  {
    "id": 44,
    "agency": "PWD",
    "work": "Status of Rahon Road Project.",
    "completionDate": "2024-05-12",
    "status": "Completed"
  },
  {
    "id": 45,
    "agency": "PWD",
    "work": "Status of Dehlon Bypass.",
    "completionDate": "2024-03-20",
    "status": "Completed"
  },
  {
    "id": 46,
    "agency": "PWD",
    "work": "Strengthening of roads near expressway entry/exit points around Ludhiana.",
    "completionDate": "2024-06-01",
    "status": "In Progress"
  },
  {
    "id": 47,
    "agency": "PWD",
    "work": "Improvement of Kohara Junction: • Widening of 1 km each on Kohara–Machiwara Road and Kohara–Sahnewal Road.",
    "completionDate": "2024-05-28",
    "status": "In Progress"
  },
  {
    "id": 48,
    "agency": "PWD",
    "work": "Greenfield/widening road connecting Machiwara Road with Chandigarh Road near entry/exit to reduce congestion at Kohara.",
    "completionDate": "2024-04-25",
    "status": "Pending"
  },
  {
    "id": 49,
    "agency": "PSIEC",
    "work": "Status of rectification of Dainik Jagran Road (opposite Fortis Hospital).",
    "completionDate": "2024-05-20",
    "status": "In Progress"
  },
  {
    "id": 50,
    "agency": "Roadways",
    "work": "Development of satellite bus terminals to reduce load on main bus stand.",
    "completionDate": "2024-09-30",
    "status": "Pending"
  },
  {
    "id": 51,
    "agency": "Roadways",
    "work": "Opening of gate between Bus Stand and Workshop.",
    "completionDate": "2024-04-10",
    "status": "Completed"
  },
  {
    "id": 52,
    "agency": "Roadways",
    "work": "Shifting of workshop / land exchange with GLADA for satellite terminals.",
    "completionDate": "2024-05-02",
    "status": "Pending"
  }
]
